<DATAPACKET Version="2.0">
    <FIELDS>
        <FIELD FieldName="ID" FieldType="Decimal"/>
        <FIELD FieldName="PRODUCTTIME" FieldType="DateTime"/>
        <FIELD FieldName="PRODUCTDESC" FieldType="String"/>
        <FIELD FieldName="TYPEDESC" FieldType="String"/>
        <FIELD FieldName="RADARSTATIONLON" FieldType="Decimal"/>
        <FIELD FieldName="RADARSTATIONLAT" FieldType="Decimal"/>
        <FIELD FieldName="RADARSTATIONHEIGHT" FieldType="Decimal"/>
        <FIELD FieldName="MINLON" FieldType="Decimal"/>
        <FIELD FieldName="MAXLON" FieldType="Decimal"/>
        <FIELD FieldName="MINLAT" FieldType="Decimal"/>
        <FIELD FieldName="MAXLAT" FieldType="Decimal"/>
        <FIELD FieldName="RESOLUTION" FieldType="Decimal"/>
        <FIELD FieldName="RANGE_" FieldType="Decimal"/>
        <FIELD FieldName="MAXREFLECTIVITY" FieldType="Decimal"/>
        <FIELD FieldName="ELEVATIONANGLE" FieldType="Decimal"/>
        <FIELD FieldName="OPERATIONALMODE" FieldType="String"/>
        <FIELD FieldName="FILEPATH" FieldType="String"/>
        <FIELD FieldName="FILESIZE" FieldType="Decimal"/>
        <FIELD FieldName="FILEMD5CHECKSUM" FieldType="String"/>
    </FIELDS>
    <ROWDATA>
        <ROW ID="348220" PRODUCTTIME="2016-06-02 16:20:20" PRODUCTDESC="" TYPEDESC="基本反射率" RADARSTATIONLON="119.541" RADARSTATIONLAT="25.991" RADARSTATIONHEIGHT="642.2136" MINLON="117.239831" MAXLON="121.842169" MINLAT="28.059435" MAXLAT="23.922565" RESOLUTION="1.00008" RANGE_="229.99988" MAXREFLECTIVITY="54" ELEVATIONANGLE="0.5" OPERATIONALMODE="Precipitation/Severe Weather" FILEPATH="../av-modules/splitScreenView/static/img/R_19_P1_5160602162020000.PNG" FILESIZE="52681" FILEMD5CHECKSUM="c934810e0d64f33404c2399d0b85efa2"/>
        <ROW ID="348217" PRODUCTTIME="2016-06-02 16:14:28" PRODUCTDESC="" TYPEDESC="基本反射率" RADARSTATIONLON="119.541" RADARSTATIONLAT="25.991" RADARSTATIONHEIGHT="642.2136" MINLON="117.239831" MAXLON="121.842169" MINLAT="28.059435" MAXLAT="23.922565" RESOLUTION="1.00008" RANGE_="229.99988" MAXREFLECTIVITY="55" ELEVATIONANGLE="0.5" OPERATIONALMODE="Precipitation/Severe Weather" FILEPATH="../av-modules/splitScreenView/static/img/R_19_P1_5160602161428000.PNG" FILESIZE="52279" FILEMD5CHECKSUM="ab36a81e8e88b4085d24cc9593f448d6"/>
        <ROW ID="348214" PRODUCTTIME="2016-06-02 16:08:35" PRODUCTDESC="" TYPEDESC="基本反射率" RADARSTATIONLON="119.541" RADARSTATIONLAT="25.991" RADARSTATIONHEIGHT="642.2136" MINLON="117.239831" MAXLON="121.842169" MINLAT="28.059435" MAXLAT="23.922565" RESOLUTION="1.00008" RANGE_="229.99988" MAXREFLECTIVITY="57" ELEVATIONANGLE="0.5" OPERATIONALMODE="Precipitation/Severe Weather" FILEPATH="../av-modules/splitScreenView/static/img/R_19_P1_5160602160835000.PNG" FILESIZE="52133" FILEMD5CHECKSUM="e62c368d2c7a989e6b7443829a8d9d78"/>
    </ROWDATA>
</DATAPACKET>